{
  "schema_version": 1,
  "generated_at": "2026-07-23T15:30:50+09:00",
  "mode": "PAPER",
  "observe_only": true,
  "production_rule_changed": false,
  "ledger_evidence": {
    "order_count": 552,
    "latest_order_at": "2026-07-23T09:31:58.548373+09:00"
  },
  "calibration_status": "PROVISIONAL_SMALL_SAMPLE",
  "execution_samples": {
    "BUY": {
      "side": "BUY",
      "orders": 7,
      "filled_orders": 4,
      "rejected_orders": 3,
      "cancelled_orders": 0,
      "status_counts": {
        "FILLED": 4,
        "REJECTED": 3
      },
      "order_fill_rate": 0.5714285714285714,
      "quantity_fill_rate": 0.5746606334841629,
      "beta_1_1_posterior_mean_fill_rate": 0.5555555555555556,
      "wilson_95_lower_fill_rate": 0.2504542304090258,
      "wilson_95_upper_fill_rate": 0.8417830777373732,
      "sample_sufficient": false
    },
    "SELL": {
      "side": "SELL",
      "orders": 7,
      "filled_orders": 6,
      "rejected_orders": 1,
      "cancelled_orders": 0,
      "status_counts": {
        "FILLED": 6,
        "REJECTED": 1
      },
      "order_fill_rate": 0.8571428571428571,
      "quantity_fill_rate": 0.7196691176470589,
      "beta_1_1_posterior_mean_fill_rate": 0.7777777777777778,
      "wilson_95_lower_fill_rate": 0.48686549668097007,
      "wilson_95_upper_fill_rate": 0.9743210440510253,
      "sample_sufficient": false
    }
  },
  "scenarios": {
    "IDEAL_FULL_FILL": {
      "A_CURRENT": {
        "total_return": -0.017502667640842073,
        "max_drawdown": -0.1906481376690169,
        "annualized_turnover": 45.83367107763751,
        "total_cost_ratio": 0.03951576003099509,
        "average_exposure": 0.7000170138908755,
        "hard_stop_count": 19,
        "trailing_stop_count": 33,
        "confirmed_reentries": 0
      },
      "R_TREND_REARM": {
        "total_return": -0.000305977118945866,
        "max_drawdown": -0.1716468902972471,
        "annualized_turnover": 23.653884299835617,
        "total_cost_ratio": 0.020334686742200663,
        "average_exposure": 0.40589809737242744,
        "hard_stop_count": 11,
        "trailing_stop_count": 16,
        "confirmed_reentries": 14
      },
      "C_CAP10": {
        "total_return": -0.018322004021282035,
        "max_drawdown": -0.14940224010256054,
        "annualized_turnover": 28.68158190071761,
        "total_cost_ratio": 0.02472592515129411,
        "average_exposure": 0.5116100471856762,
        "hard_stop_count": 19,
        "trailing_stop_count": 33,
        "confirmed_reentries": 0
      },
      "C_CAP08": {
        "total_return": -0.012852581828408316,
        "max_drawdown": -0.12047355017527128,
        "annualized_turnover": 22.934248088279176,
        "total_cost_ratio": 0.019768299039837182,
        "average_exposure": 0.40880604547563754,
        "hard_stop_count": 19,
        "trailing_stop_count": 33,
        "confirmed_reentries": 0
      }
    },
    "STABILIZED_POSTERIOR_MEAN": {
      "A_CURRENT": {
        "total_return": 0.023500612201362348,
        "max_drawdown": -0.19686129018322474,
        "annualized_turnover": 36.69325529089539,
        "total_cost_ratio": 0.03172327076056916,
        "average_exposure": 0.6351016381534825,
        "hard_stop_count": 24,
        "trailing_stop_count": 31,
        "confirmed_reentries": 0
      },
      "R_TREND_REARM": {
        "total_return": 0.03496505567101371,
        "max_drawdown": -0.15225690815834192,
        "annualized_turnover": 21.334197777701903,
        "total_cost_ratio": 0.018188642087333163,
        "average_exposure": 0.38743600747265,
        "hard_stop_count": 12,
        "trailing_stop_count": 18,
        "confirmed_reentries": 12
      },
      "C_CAP10": {
        "total_return": 0.031006796677469417,
        "max_drawdown": -0.12165065078520876,
        "annualized_turnover": 24.910139434348277,
        "total_cost_ratio": 0.021463325746701782,
        "average_exposure": 0.4941143575749904,
        "hard_stop_count": 16,
        "trailing_stop_count": 34,
        "confirmed_reentries": 0
      },
      "C_CAP08": {
        "total_return": 0.018633608684909264,
        "max_drawdown": -0.1311295056255175,
        "annualized_turnover": 19.53888603936724,
        "total_cost_ratio": 0.01682756651744199,
        "average_exposure": 0.3689388962525362,
        "hard_stop_count": 16,
        "trailing_stop_count": 33,
        "confirmed_reentries": 0
      }
    },
    "STABILIZED_WILSON_LOWER": {
      "A_CURRENT": {
        "total_return": 0.01573061404050491,
        "max_drawdown": -0.1757544817297989,
        "annualized_turnover": 30.0259475996046,
        "total_cost_ratio": 0.02588121600974431,
        "average_exposure": 0.5465974701391448,
        "hard_stop_count": 16,
        "trailing_stop_count": 46,
        "confirmed_reentries": 0
      },
      "R_TREND_REARM": {
        "total_return": -0.11768611662433526,
        "max_drawdown": -0.21119831669810707,
        "annualized_turnover": 19.082572893878492,
        "total_cost_ratio": 0.01632017217654859,
        "average_exposure": 0.3795954989115313,
        "hard_stop_count": 18,
        "trailing_stop_count": 32,
        "confirmed_reentries": 9
      },
      "C_CAP10": {
        "total_return": -0.015338737992205864,
        "max_drawdown": -0.13784749789953832,
        "annualized_turnover": 20.251546451634187,
        "total_cost_ratio": 0.017446669196263222,
        "average_exposure": 0.405319738615855,
        "hard_stop_count": 23,
        "trailing_stop_count": 40,
        "confirmed_reentries": 0
      },
      "C_CAP08": {
        "total_return": -0.07834449112307851,
        "max_drawdown": -0.14025354648024235,
        "annualized_turnover": 15.41203639463205,
        "total_cost_ratio": 0.01325679876176828,
        "average_exposure": 0.29654238108157693,
        "hard_stop_count": 28,
        "trailing_stop_count": 41,
        "confirmed_reentries": 0
      }
    }
  },
  "candidate": "R_TREND_REARM",
  "baseline": "A_CURRENT",
  "scenario_checks": [
    {
      "scenario": "IDEAL_FULL_FILL",
      "return_improves": true,
      "drawdown_improves": true,
      "turnover_improves": true,
      "passed": true,
      "candidate_return": -0.000305977118945866,
      "baseline_return": -0.017502667640842073,
      "candidate_mdd": -0.1716468902972471,
      "baseline_mdd": -0.1906481376690169,
      "candidate_turnover": 23.653884299835617,
      "baseline_turnover": 45.83367107763751
    },
    {
      "scenario": "STABILIZED_POSTERIOR_MEAN",
      "return_improves": true,
      "drawdown_improves": true,
      "turnover_improves": true,
      "passed": true,
      "candidate_return": 0.03496505567101371,
      "baseline_return": 0.023500612201362348,
      "candidate_mdd": -0.15225690815834192,
      "baseline_mdd": -0.19686129018322474,
      "candidate_turnover": 21.334197777701903,
      "baseline_turnover": 36.69325529089539
    },
    {
      "scenario": "STABILIZED_WILSON_LOWER",
      "return_improves": false,
      "drawdown_improves": false,
      "turnover_improves": true,
      "passed": false,
      "candidate_return": -0.11768611662433526,
      "baseline_return": 0.01573061404050491,
      "candidate_mdd": -0.21119831669810707,
      "baseline_mdd": -0.1757544817297989,
      "candidate_turnover": 19.082572893878492,
      "baseline_turnover": 30.0259475996046
    }
  ],
  "risk_control_gate": {
    "thresholds": {
      "total_return_floor": -0.1,
      "max_drawdown_floor": -0.2,
      "annualized_turnover_ceiling": 30.0
    },
    "checks": [
      {
        "variant": "C_CAP10",
        "all_scenarios_pass": true,
        "scenario_checks": [
          {
            "scenario": "IDEAL_FULL_FILL",
            "passed": true,
            "total_return": -0.018322004021282035,
            "max_drawdown": -0.14940224010256054,
            "annualized_turnover": 28.68158190071761
          },
          {
            "scenario": "STABILIZED_POSTERIOR_MEAN",
            "passed": true,
            "total_return": 0.031006796677469417,
            "max_drawdown": -0.12165065078520876,
            "annualized_turnover": 24.910139434348277
          },
          {
            "scenario": "STABILIZED_WILSON_LOWER",
            "passed": true,
            "total_return": -0.015338737992205864,
            "max_drawdown": -0.13784749789953832,
            "annualized_turnover": 20.251546451634187
          }
        ]
      },
      {
        "variant": "C_CAP08",
        "all_scenarios_pass": true,
        "scenario_checks": [
          {
            "scenario": "IDEAL_FULL_FILL",
            "passed": true,
            "total_return": -0.012852581828408316,
            "max_drawdown": -0.12047355017527128,
            "annualized_turnover": 22.934248088279176
          },
          {
            "scenario": "STABILIZED_POSTERIOR_MEAN",
            "passed": true,
            "total_return": 0.018633608684909264,
            "max_drawdown": -0.1311295056255175,
            "annualized_turnover": 19.53888603936724
          },
          {
            "scenario": "STABILIZED_WILSON_LOWER",
            "passed": true,
            "total_return": -0.07834449112307851,
            "max_drawdown": -0.14025354648024235,
            "annualized_turnover": 15.41203639463205
          }
        ]
      }
    ],
    "robust_variants": [
      "C_CAP10",
      "C_CAP08"
    ],
    "fallback_available": true,
    "production_rule_changed": false,
    "manual_review_required": true
  },
  "promotion_gate": {
    "ready": false,
    "minimum_side_sample": 30,
    "sample_ready": false,
    "all_execution_scenarios_pass": false,
    "manual_review_required": true,
    "blockers": [
      "post-hardening BUY and SELL samples have not each reached 30 orders",
      "trend-rearm does not improve return, drawdown, and turnover in every execution scenario"
    ]
  },
  "sources": [
    "/app/reports/analysis/paper_ledger_latest/order_lifecycle.csv",
    "/app/reports/analysis/paper_reentry_experiments/pass_only/metrics.json"
  ]
}